<?xml version="1.0" encoding="UTF-8"?>
<objects serializationModel="Studio.02.02.00">
	<object class="AudioFile" id="{531023a7-7a6a-4c56-8997-2163321a017b}">
		<property name="assetPath">
			<value>Elemental - Evil Cast Loop Paralyze_2.wav</value>
		</property>
		<property name="frequencyInKHz">
			<value>48</value>
		</property>
		<property name="channelCount">
			<value>1</value>
		</property>
		<property name="length">
			<value>1.4314583333333333</value>
		</property>
		<relationship name="masterAssetFolder">
			<destination>{4a5e4dcc-d504-4bec-9032-0bd161c570ee}</destination>
		</relationship>
	</object>
</objects>
